VecStatsGraph
