Metadata-Version: 1.0
Name: VecStatsGraph3d
Version: 1.3
Summary: Spherical statistcis analysis
Home-page: https://github.com/IvanDragoJr/VecStatsGraph3d
Author: Pedro Alfonso
Author-email: p.alfonso.jimenez@gmail.com
License: Apache 2.0
Platform: UNKNOWN
